NeuralNetPy/__init__.py
NeuralNetPy/activations/__init__.py
NeuralNetPy/activations/activations.py
NeuralNetPy/layers/__init__.py
NeuralNetPy/layers/layers.py
NeuralNetPy/losses/__init__.py
NeuralNetPy/losses/losses.py
NeuralNetPy/models/__init__.py
NeuralNetPy/models/models.py
NeuralNetPy/optimizers/__init__.py
NeuralNetPy/optimizers/optimizers.py
NeuralNetPy/utils/__init__.py
NeuralNetPy/utils/utils.py
NeuralNetPy-0.0.5.dist-info/METADATA
NeuralNetPy-0.0.5.dist-info/WHEEL
NeuralNetPy-0.0.5.dist-info/top_level.txt
NeuralNetPy-0.0.5.dist-info/RECORD
