Metadata-Version: 2.1
Name: NeuralNetPy
Version: 0.0.5
Summary: NeuralNetPy is a neural network library created using numpy that allows you to create, train, and save deep learning models.
Home-page: UNKNOWN
Author: Joel Maldonado-Ruiz
Author-email: jmaldonadoruiz0@gmail.com
License: GNU General Public License v3.0
Keywords: Neural Network,Python,AI,Numpy,Deep Learning
Platform: UNKNOWN
Classifier: Development Status :: 3 - Alpha
Classifier: Environment :: Console
Classifier: Intended Audience :: Science/Research
Classifier: License :: OSI Approved :: GNU General Public License v3 (GPLv3)
Classifier: Natural Language :: English
Classifier: Operating System :: OS Independent
Classifier: Programming Language :: Python :: 3
Classifier: Topic :: Scientific/Engineering :: Artificial Intelligence
Requires-Dist: matplotlib (>=3.6.3)
Requires-Dist: numpy (>=1.23.5)
